Metadata-Version: 2.4
Name: py-tree-sitter-swift
Version: 0.0.1
Summary: Swift grammar for tree-sitter, fork of main
License-Expression: MIT
Project-URL: Homepage, https://github.com/aboutcode-org/tree-sitter-swift
Keywords: incremental,parsing,tree-sitter,swift
Classifier: Intended Audience :: Developers
Classifier: Topic :: Software Development :: Compilers
Classifier: Topic :: Text Processing :: Linguistic
Classifier: Typing :: Typed
Requires-Python: >=3.9
License-File: LICENSE
Provides-Extra: core
Requires-Dist: tree-sitter~=0.23; extra == "core"
Dynamic: license-file
